teletvg/TeleTVG.pdf
teletvg/TeleTVG.py
teletvg/__init__.py
teletvg/emo.py
teletvg/emoj.txt
teletvg/dbase/__init__.py
teletvg/dbase/archiver7z.py
teletvg/dbase/datab.py
teletvg_karjakak-1.3.8.dist-info/LICENSE
teletvg_karjakak-1.3.8.dist-info/METADATA
teletvg_karjakak-1.3.8.dist-info/WHEEL
teletvg_karjakak-1.3.8.dist-info/entry_points.txt
teletvg_karjakak-1.3.8.dist-info/top_level.txt
teletvg_karjakak-1.3.8.dist-info/RECORD
