Metadata-Version: 2.1
Name: teletvg-karjakak
Version: 1.3.8
Summary: TeleTVG for sending message to multiple users in group with text-expander function.
Home-page: https://github.com/kakkarja/TeleTVG
Author: karjakak
Author-email: kakkarja.github@gmail.com
License: BSD3 License
Platform: UNKNOWN
Classifier: Environment :: Win32 (MS Windows)
Classifier: Environment :: MacOS X
Classifier: Intended Audience :: End Users/Desktop
Classifier: Programming Language :: Python :: 3.10
Classifier: License :: OSI Approved :: BSD License
Requires-Python: >=3.10
License-File: LICENSE
Requires-Dist: telethon (>=1.22.0)
Requires-Dist: Clien-karjakak (>=0.1.0)
Requires-Dist: py7zr (>=0.16.2)
